agents/__init__.py
agents/server.py
amajakai14_mcp_agents-0.1.4.dist-info/METADATA
amajakai14_mcp_agents-0.1.4.dist-info/WHEEL
amajakai14_mcp_agents-0.1.4.dist-info/entry_points.txt
amajakai14_mcp_agents-0.1.4.dist-info/RECORD
